odoo/addons/account_brand/README.rst
odoo/addons/account_brand/__init__.py
odoo/addons/account_brand/__manifest__.py
odoo/addons/account_brand/i18n/account_brand.pot
odoo/addons/account_brand/i18n/de.po
odoo/addons/account_brand/i18n/es.po
odoo/addons/account_brand/i18n/hr.po
odoo/addons/account_brand/i18n/zh_CN.po
odoo/addons/account_brand/migrations/12.0.2.0.0/post-migration.py
odoo/addons/account_brand/migrations/12.0.2.0.0/pre-migration.py
odoo/addons/account_brand/models/__init__.py
odoo/addons/account_brand/models/account_invoice.py
odoo/addons/account_brand/models/res_partner_account_brand.py
odoo/addons/account_brand/readme/CONFIGURE.rst
odoo/addons/account_brand/readme/CONTRIBUTORS.rst
odoo/addons/account_brand/readme/CREDITS.rst
odoo/addons/account_brand/readme/DESCRIPTION.rst
odoo/addons/account_brand/readme/USAGE.rst
odoo/addons/account_brand/security/res_partner_account_brand.xml
odoo/addons/account_brand/static/description/icon.png
odoo/addons/account_brand/static/description/index.html
odoo/addons/account_brand/tests/__init__.py
odoo/addons/account_brand/tests/test_account_analytic_invoice.py
odoo/addons/account_brand/tests/test_account_invoice.py
odoo/addons/account_brand/tests/test_brand_mixin.py
odoo/addons/account_brand/views/account_invoice.xml
odoo/addons/account_brand/views/res_partner_account_brand.xml
odoo12_addon_account_brand-12.0.3.1.1.dist-info/METADATA
odoo12_addon_account_brand-12.0.3.1.1.dist-info/WHEEL
odoo12_addon_account_brand-12.0.3.1.1.dist-info/top_level.txt
odoo12_addon_account_brand-12.0.3.1.1.dist-info/RECORD
